{
   "ContextClassName": "ACCDBContext",
   "ContextNamespace": null,
   "DefaultDacpacSchema": null,
   "DoNotCombineNamespace": false,
   "IdReplace": false,
   "IncludeConnectionString": false,
   "ModelNamespace": null,
   "OutputContextPath": null,
   "OutputPath": null,
   "ProjectRootNamespace": "iChiba.ACC.Model",
   "SelectedHandlebarsLanguage": 0,
   "SelectedToBeGenerated": 0,
   "Tables": [
      {
         "HasPrimaryKey": true,
         "Name": "[dbo].[ACCOUNT]"
      },
      {
         "HasPrimaryKey": true,
         "Name": "[dbo].[BANK_ACCOUNT]"
      },
      {
         "HasPrimaryKey": true,
         "Name": "[dbo].[CURRENCY]"
      },
      {
         "HasPrimaryKey": true,
         "Name": "[dbo].[DEPARTMENT]"
      },
      {
         "HasPrimaryKey": true,
         "Name": "[dbo].[EMPLOYEE]"
      },
      {
         "HasPrimaryKey": true,
         "Name": "[dbo].[OBJECT]"
      },
      {
         "HasPrimaryKey": true,
         "Name": "[dbo].[OBJECT_GROUP]"
      },
      {
         "HasPrimaryKey": true,
         "Name": "[dbo].[STATISTIC]"
      }
   ],
   "UseDatabaseNames": false,
   "UseFluentApiOnly": true,
   "UseHandleBars": false,
   "UseInflector": false,
   "UseLegacyPluralizer": false,
   "UseSpatial": false
}